chatapi_toolkit/__init__.py
chatapi_toolkit/asynctool.py
chatapi_toolkit/chattool.py
chatapi_toolkit/checkpoint.py
chatapi_toolkit/cli.py
chatapi_toolkit/proxy.py
chatapi_toolkit/request.py
chatapi_toolkit/response.py
chatapi_toolkit/tokencalc.py
chatapi_toolkit-2.0.0.dist-info/LICENSE
chatapi_toolkit-2.0.0.dist-info/METADATA
chatapi_toolkit-2.0.0.dist-info/WHEEL
chatapi_toolkit-2.0.0.dist-info/entry_points.txt
chatapi_toolkit-2.0.0.dist-info/top_level.txt
chatapi_toolkit-2.0.0.dist-info/RECORD
