Metadata-Version: 2.1
Name: chatapi-toolkit
Version: 2.0.0
Summary: A short wrapper of the Chatapi Toolkit.
Home-page: https://github.com/cubenlp/chatapi_toolkit
Author: Rex Wang
Author-email: 1073853456@qq.com
License: MIT license
Keywords: chatapi_toolkit
Platform: UNKNOWN
Classifier: Development Status :: 2 - Pre-Alpha
Classifier: Intended Audience :: Developers
Classifier: License :: OSI Approved :: MIT License
Classifier: Natural Language :: English
Classifier: Programming Language :: Python :: 3.8
Classifier: Programming Language :: Python :: 3.9
Classifier: Programming Language :: Python :: 3.10
Requires-Python: >=3.7
Requires-Dist: Click >=7.0
Requires-Dist: requests >=2.20
Requires-Dist: responses >=0.23
Requires-Dist: tqdm >=4.60
Requires-Dist: aiohttp >=3.8
Requires-Dist: tiktoken >=0.4.0
